TOPO_101703292/101703292.py
TOPO_101703292/3292.py
TOPSIS_ANALYSIS_kriti-1.1.2.dist-info/LICENSE.txt
TOPSIS_ANALYSIS_kriti-1.1.2.dist-info/METADATA
TOPSIS_ANALYSIS_kriti-1.1.2.dist-info/WHEEL
TOPSIS_ANALYSIS_kriti-1.1.2.dist-info/entry_points.txt
TOPSIS_ANALYSIS_kriti-1.1.2.dist-info/top_level.txt
TOPSIS_ANALYSIS_kriti-1.1.2.dist-info/RECORD
