Metadata-Version: 2.1
Name: TOPSIS-ANALYSIS-kriti
Version: 1.1.2
Summary: A Python package to evaluate ranks of a Multiple Criteria Decision Making Problem(MCDM) using Technique for Order of Preference by Similarity to Ideal Solution(TOPSIS)
Home-page: UNKNOWN
Author: Kriti Pandey
Author-email: kritip105@gmail.com
License: MIT
Platform: UNKNOWN
Classifier: License :: OSI Approved :: MIT License
Classifier: Programming Language :: Python :: 3
Classifier: Programming Language :: Python :: 3.7
Requires-Dist: numpy
Requires-Dist: pandas
